LICENSE
README.md
nautobot_ssot_ipfabric/__init__.py
nautobot_ssot_ipfabric/diffsync/__init__.py
nautobot_ssot_ipfabric/diffsync/adapter_ipfabric.py
nautobot_ssot_ipfabric/diffsync/adapter_nautobot.py
nautobot_ssot_ipfabric/diffsync/adapters_shared.py
nautobot_ssot_ipfabric/diffsync/diffsync_models.py
nautobot_ssot_ipfabric/jobs.py
nautobot_ssot_ipfabric/signals.py
nautobot_ssot_ipfabric/static/nautobot_ssot_ipfabric/ipfabric.png
nautobot_ssot_ipfabric/static/nautobot_ssot_ipfabric/ipfabric_logo.png
nautobot_ssot_ipfabric/tests/__init__.py
nautobot_ssot_ipfabric/tests/fixtures/__init__.py
nautobot_ssot_ipfabric/tests/fixtures/get_device_inventory.json
nautobot_ssot_ipfabric/tests/fixtures/get_interface_inventory.json
nautobot_ssot_ipfabric/tests/fixtures/get_sites.json
nautobot_ssot_ipfabric/tests/fixtures/get_vlans.json
nautobot_ssot_ipfabric/tests/test_ipfabric_adapter.py
nautobot_ssot_ipfabric/tests/test_jobs.py
nautobot_ssot_ipfabric/tests/test_nautobot_adapter.py
nautobot_ssot_ipfabric/tests/test_nbutils.py
nautobot_ssot_ipfabric/utilities/__init__.py
nautobot_ssot_ipfabric/utilities/nbutils.py
nautobot_ssot_ipfabric/utilities/test_utils.py
nautobot_ssot_ipfabric/workers.py
nautobot_ssot_ipfabric-2.0.2.dist-info/LICENSE
nautobot_ssot_ipfabric-2.0.2.dist-info/METADATA
nautobot_ssot_ipfabric-2.0.2.dist-info/WHEEL
nautobot_ssot_ipfabric-2.0.2.dist-info/entry_points.txt
nautobot_ssot_ipfabric-2.0.2.dist-info/RECORD
