Metadata-Version: 2.1
Name: nautobot-ssot-ipfabric
Version: 2.0.2
Summary: Nautobot SSoT IPFabric
Home-page: https://github.com/networktocode-llc/nautobot-plugin-ssot-ipfabric
License: Apache-2.0
Keywords: nautobot,nautobot-plugin
Author: Network to Code, LLC
Author-email: info@networktocode.com
Requires-Python: >=3.7.1,<4.0
Classifier: License :: OSI Approved :: Apache Software License
Classifier: Programming Language :: Python :: 3
Classifier: Programming Language :: Python :: 3.8
Classifier: Programming Language :: Python :: 3.9
Classifier: Programming Language :: Python :: 3.10
Classifier: Programming Language :: Python :: 3.11
Provides-Extra: nautobot
Requires-Dist: ipfabric (>=6.0.9,<6.1.0)
Requires-Dist: ipfabric-diagrams (>=6.0.2,<6.1.0)
Requires-Dist: nautobot (>=1.2.0,<2.0.0) ; extra == "nautobot"
Requires-Dist: nautobot-ssot (>=1.0.1,<2.0.0)
Requires-Dist: netutils (>=1.0.0,<2.0.0)
Project-URL: Repository, https://github.com/networktocode-llc/nautobot-plugin-ssot-ipfabric
